kirons_py3_module/Colors.py
kirons_py3_module/ConsoleColors.py
kirons_py3_module/Window.py
kirons_py3_module/__init__.py
kirons_py3_module-5.dist-info/METADATA
kirons_py3_module-5.dist-info/RECORD
kirons_py3_module-5.dist-info/WHEEL
kirons_py3_module-5.dist-info/top_level.txt
