Metadata-Version: 2.1
Name: kirons-py3-module
Version: 5
Summary: A simple module made by KironDevCoder for hard-to-program programs
Home-page: https://kirons-py3-module.readthedocs.io
Author: KironDevCoder
Author-email: mojanghouse@gmail.com
License: UNKNOWN
Platform: UNKNOWN
Classifier: Programming Language :: Python :: 3
Classifier: License :: OSI Approved :: MIT License
Classifier: Operating System :: OS Independent
